[{"cisAgents":[{"agentName":"Worker-1","averageCallDuration":100.31,"averageScore":82,"businessCompletedNum":9,"complaintNum":2,"erLang":13,"id":1,"illegalOperationNum":0,"speakSpeed":6.64},{"agentName":"Worker-2","averageCallDuration":75.18,"averageScore":9.02,"businessCompletedNum":5,"complaintNum":2,"erLang":19,"id":2,"illegalOperationNum":1,"speakSpeed":5.8},{"agentName":"Worker-3","averageCallDuration":72.74,"averageScore":26.52,"businessCompletedNum":4,"complaintNum":2,"erLang":8,"id":3,"illegalOperationNum":0,"speakSpeed":6.38},{"agentName":"Worker-4","averageCallDuration":138.2,"averageScore":80.14,"businessCompletedNum":6,"complaintNum":2,"erLang":2,"id":4,"illegalOperationNum":1,"speakSpeed":6.75},{"agentName":"Worker-5","averageCallDuration":68.36,"averageScore":2.76,"businessCompletedNum":8,"complaintNum":0,"erLang":6,"id":5,"illegalOperationNum":0,"speakSpeed":5.05},{"agentName":"Worker-6","averageCallDuration":126.2,"averageScore":13.98,"businessCompletedNum":10,"complaintNum":1,"erLang":15,"id":6,"illegalOperationNum":1,"speakSpeed":5.49},{"agentName":"Worker-7","averageCallDuration":123.39,"averageScore":5.05,"businessCompletedNum":5,"complaintNum":0,"erLang":11,"id":7,"illegalOperationNum":1,"speakSpeed":5.1},{"agentName":"Worker-8","averageCallDuration":110.72,"averageScore":34.09,"businessCompletedNum":6,"complaintNum":0,"erLang":7,"id":8,"illegalOperationNum":1,"speakSpeed":6.95},{"agentName":"Worker-9","averageCallDuration":78.46,"averageScore":61.33,"businessCompletedNum":3,"complaintNum":2,"erLang":7,"id":9,"illegalOperationNum":1,"speakSpeed":6.15},{"agentName":"Worker-10","averageCallDuration":135.76,"averageScore":69.54,"businessCompletedNum":10,"complaintNum":2,"erLang":9,"id":10,"illegalOperationNum":0,"speakSpeed":6.54}],"departmentId":1,"departmentName":"Group-1"},{"cisAgents":[{"agentName":"Worker-11","averageCallDuration":71.01,"averageScore":53.74,"businessCompletedNum":4,"complaintNum":2,"erLang":10,"id":11,"illegalOperationNum":1,"speakSpeed":7},{"agentName":"Worker-12","averageCallDuration":150.02,"averageScore":19.11,"businessCompletedNum":2,"complaintNum":0,"erLang":15,"id":12,"illegalOperationNum":0,"speakSpeed":5.91},{"agentName":"Worker-13","averageCallDuration":140.92,"averageScore":17,"businessCompletedNum":2,"complaintNum":2,"erLang":19,"id":13,"illegalOperationNum":0,"speakSpeed":6.6},{"agentName":"Worker-14","averageCallDuration":103.3,"averageScore":78.6,"businessCompletedNum":4,"complaintNum":1,"erLang":19,"id":14,"illegalOperationNum":1,"speakSpeed":5.98},{"agentName":"Worker-15","averageCallDuration":132.69,"averageScore":68.83,"businessCompletedNum":3,"complaintNum":1,"erLang":16,"id":15,"illegalOperationNum":1,"speakSpeed":5.44},{"agentName":"Worker-16","averageCallDuration":144.96,"averageScore":61.68,"businessCompletedNum":7,"complaintNum":1,"erLang":13,"id":16,"illegalOperationNum":0,"speakSpeed":5.96},{"agentName":"Worker-17","averageCallDuration":133.98,"averageScore":23.08,"businessCompletedNum":6,"complaintNum":0,"erLang":7,"id":17,"illegalOperationNum":0,"speakSpeed":5.28},{"agentName":"Worker-18","averageCallDuration":107.62,"averageScore":82.03,"businessCompletedNum":3,"complaintNum":0,"erLang":6,"id":18,"illegalOperationNum":0,"speakSpeed":5.91},{"agentName":"Worker-19","averageCallDuration":80.19,"averageScore":27.33,"businessCompletedNum":6,"complaintNum":0,"erLang":16,"id":19,"illegalOperationNum":0,"speakSpeed":6.49},{"agentName":"Worker-20","averageCallDuration":108.74,"averageScore":85.31,"businessCompletedNum":6,"complaintNum":1,"erLang":11,"id":20,"illegalOperationNum":0,"speakSpeed":6.16}],"departmentId":2,"departmentName":"Group-2"},{"cisAgents":[{"agentName":"Worker-21","averageCallDuration":123.85,"averageScore":45.15,"businessCompletedNum":9,"complaintNum":1,"erLang":18,"id":21,"illegalOperationNum":1,"speakSpeed":5.72},{"agentName":"Worker-22","averageCallDuration":102.19,"averageScore":16.29,"businessCompletedNum":1,"complaintNum":2,"erLang":20,"id":22,"illegalOperationNum":0,"speakSpeed":5.03},{"agentName":"Worker-23","averageCallDuration":147.85,"averageScore":23.17,"businessCompletedNum":7,"complaintNum":2,"erLang":7,"id":23,"illegalOperationNum":0,"speakSpeed":5.29},{"agentName":"Worker-24","averageCallDuration":102.8,"averageScore":84.29,"businessCompletedNum":1,"complaintNum":2,"erLang":4,"id":24,"illegalOperationNum":0,"speakSpeed":5.39},{"agentName":"Worker-25","averageCallDuration":124.85,"averageScore":64.12,"businessCompletedNum":4,"complaintNum":0,"erLang":17,"id":25,"illegalOperationNum":0,"speakSpeed":5.47},{"agentName":"Worker-26","averageCallDuration":101.63,"averageScore":78.59,"businessCompletedNum":1,"complaintNum":1,"erLang":17,"id":26,"illegalOperationNum":1,"speakSpeed":6.65},{"agentName":"Worker-27","averageCallDuration":71.85,"averageScore":92.2,"businessCompletedNum":1,"complaintNum":1,"erLang":17,"id":27,"illegalOperationNum":1,"speakSpeed":5.55},{"agentName":"Worker-28","averageCallDuration":148.86,"averageScore":20.46,"businessCompletedNum":5,"complaintNum":2,"erLang":18,"id":28,"illegalOperationNum":1,"speakSpeed":5.13},{"agentName":"Worker-29","averageCallDuration":96.65,"averageScore":35.93,"businessCompletedNum":7,"complaintNum":1,"erLang":8,"id":29,"illegalOperationNum":1,"speakSpeed":6.24},{"agentName":"Worker-30","averageCallDuration":124,"averageScore":93.3,"businessCompletedNum":3,"complaintNum":1,"erLang":5,"id":30,"illegalOperationNum":1,"speakSpeed":6.85}],"departmentId":3,"departmentName":"Group-3"},{"cisAgents":[{"agentName":"Worker-31","averageCallDuration":91.48,"averageScore":59.65,"businessCompletedNum":2,"complaintNum":0,"erLang":18,"id":31,"illegalOperationNum":1,"speakSpeed":5.28},{"agentName":"Worker-32","averageCallDuration":148.94,"averageScore":31.97,"businessCompletedNum":7,"complaintNum":1,"erLang":11,"id":32,"illegalOperationNum":1,"speakSpeed":6.85},{"agentName":"Worker-33","averageCallDuration":96.16,"averageScore":93.5,"businessCompletedNum":1,"complaintNum":1,"erLang":19,"id":33,"illegalOperationNum":1,"speakSpeed":5.78},{"agentName":"Worker-34","averageCallDuration":72.3,"averageScore":88.05,"businessCompletedNum":2,"complaintNum":1,"erLang":2,"id":34,"illegalOperationNum":0,"speakSpeed":6.33},{"agentName":"Worker-35","averageCallDuration":103.06,"averageScore":26.76,"businessCompletedNum":10,"complaintNum":0,"erLang":9,"id":35,"illegalOperationNum":0,"speakSpeed":5.16},{"agentName":"Worker-36","averageCallDuration":109.99,"averageScore":71.35,"businessCompletedNum":1,"complaintNum":2,"erLang":11,"id":36,"illegalOperationNum":0,"speakSpeed":5.25},{"agentName":"Worker-37","averageCallDuration":75.29,"averageScore":81.4,"businessCompletedNum":6,"complaintNum":0,"erLang":14,"id":37,"illegalOperationNum":0,"speakSpeed":5.15},{"agentName":"Worker-38","averageCallDuration":131.41,"averageScore":45.21,"businessCompletedNum":3,"complaintNum":0,"erLang":8,"id":38,"illegalOperationNum":0,"speakSpeed":6.01},{"agentName":"Worker-39","averageCallDuration":137.84,"averageScore":16.59,"businessCompletedNum":2,"complaintNum":2,"erLang":7,"id":39,"illegalOperationNum":0,"speakSpeed":6.24},{"agentName":"Worker-40","averageCallDuration":146.4,"averageScore":42.52,"businessCompletedNum":8,"complaintNum":2,"erLang":10,"id":40,"illegalOperationNum":1,"speakSpeed":5.26}],"departmentId":4,"departmentName":"Group-4"},{"cisAgents":[{"agentName":"Worker-41","averageCallDuration":124.06,"averageScore":31.69,"businessCompletedNum":1,"complaintNum":2,"erLang":14,"id":41,"illegalOperationNum":0,"speakSpeed":5.92},{"agentName":"Worker-42","averageCallDuration":89.58,"averageScore":26.7,"businessCompletedNum":2,"complaintNum":1,"erLang":8,"id":42,"illegalOperationNum":1,"speakSpeed":5.09},{"agentName":"Worker-43","averageCallDuration":144.25,"averageScore":29.54,"businessCompletedNum":9,"complaintNum":0,"erLang":17,"id":43,"illegalOperationNum":0,"speakSpeed":5.8},{"agentName":"Worker-44","averageCallDuration":100.82,"averageScore":25.63,"businessCompletedNum":2,"complaintNum":1,"erLang":4,"id":44,"illegalOperationNum":0,"speakSpeed":6.1},{"agentName":"Worker-45","averageCallDuration":150.37,"averageScore":0.67,"businessCompletedNum":4,"complaintNum":1,"erLang":6,"id":45,"illegalOperationNum":0,"speakSpeed":6.21},{"agentName":"Worker-46","averageCallDuration":72.45,"averageScore":20.65,"businessCompletedNum":9,"complaintNum":0,"erLang":1,"id":46,"illegalOperationNum":1,"speakSpeed":5.12},{"agentName":"Worker-47","averageCallDuration":152.71,"averageScore":42.06,"businessCompletedNum":4,"complaintNum":1,"erLang":9,"id":47,"illegalOperationNum":0,"speakSpeed":5.96},{"agentName":"Worker-48","averageCallDuration":102.55,"averageScore":25.73,"businessCompletedNum":5,"complaintNum":1,"erLang":10,"id":48,"illegalOperationNum":0,"speakSpeed":5.06},{"agentName":"Worker-49","averageCallDuration":70.17,"averageScore":15.96,"businessCompletedNum":2,"complaintNum":0,"erLang":17,"id":49,"illegalOperationNum":1,"speakSpeed":5.37},{"agentName":"Worker-50","averageCallDuration":112.21,"averageScore":33.46,"businessCompletedNum":3,"complaintNum":2,"erLang":17,"id":50,"illegalOperationNum":0,"speakSpeed":6.71}],"departmentId":5,"departmentName":"Group-5"}]